[
  {
    "id": "a0v",
    "name": " SEML Biarritz Ocean"
  },
  {
    "id": "l3o",
    "name": "ABATTOIR D'OSSAU"
  },
  {
    "id": "a4c",
    "name": "Abattoir du Pays de Soule"
  },
  {
    "id": "d7o",
    "name": "AFAFAF d’Abidos et Os-Marsillon"
  },
  {
    "id": "c7s",
    "name": "AFAFAF d’OLORON SAINTE MARIE, ESCOUT et PRECILHON"
  },
  {
    "id": "a2u",
    "name": "AFP BAIGURA MENDI"
  },
  {
    "id": "a3l",
    "name": "AFP URSUYA MENDI"
  },
  {
    "id": "g5n",
    "name": "AFR D'ESPECHEDE"
  },
  {
    "id": "t9g",
    "name": "AFR DE BIDACHE"
  },
  {
    "id": "a6t",
    "name": "AFR de Sarpourenx"
  },
  {
    "id": "n1s",
    "name": "AFR DU VILLAGE DESPECHEDE"
  },
  {
    "id": "t4z",
    "name": "Agence d'Attractivité et de Développement Touristique"
  },
  {
    "id": "g3h",
    "name": "Agence Départementale du Numérique"
  },
  {
    "id": "n2a",
    "name": "Agence Publique de Gestion Locale"
  },
  {
    "id": "l7m",
    "name": "Agence transfrontalière pour le développement de l'Eurocité basque Bayonne-San Sebastián"
  },
  {
    "id": "x2c",
    "name": "Agglomération Côte basque-Adour "
  },
  {
    "id": "a4l",
    "name": "ANGLET TOURISME"
  },
  {
    "id": "a5x",
    "name": "ANTIC Pays Basque"
  },
  {
    "id": "a6p",
    "name": "ASA d'Espes Undurein"
  },
  {
    "id": "a7r",
    "name": "ASA d'IRRIGATION d'ARGAGNON"
  },
  {
    "id": "a2f",
    "name": "ASA d'irrigation d'ARGELOS-ASTIS"
  },
  {
    "id": "a3r",
    "name": "ASA D'IRRIGATION D'ORTHEZ"
  },
  {
    "id": "a3p",
    "name": "ASA d'irrigation de CAUBIOS-LOOS"
  },
  {
    "id": "a2h",
    "name": "ASA d'irrigation de DENGUIN"
  },
  {
    "id": "a2l",
    "name": "ASA d'irrigation de l'AUBIN"
  },
  {
    "id": "c2d",
    "name": "ASA d'irrigation de la Vallée du Làa"
  },
  {
    "id": "a2m",
    "name": "ASA d'irrigation de LACQ-AUDEJOS"
  },
  {
    "id": "y7p",
    "name": "ASA d'irrigation de Lanneplaà-Ste Suzanne"
  },
  {
    "id": "a2i",
    "name": "ASA d'irrigation de MASLACQ"
  },
  {
    "id": "a2g",
    "name": "ASA d'irrigation du LOUTS-AMONT"
  },
  {
    "id": "a6a",
    "name": "ASA d'irrigation d'Arzacq"
  },
  {
    "id": "f1e",
    "name": "ASA d'IRRIGATION d'OSSENX"
  },
  {
    "id": "a7e",
    "name": "ASA de Bastanes"
  },
  {
    "id": "a6s",
    "name": "ASA de Bentayou"
  },
  {
    "id": "s7b",
    "name": "ASA de BIDACHE"
  },
  {
    "id": "a7a",
    "name": "ASA de Bournos"
  },
  {
    "id": "a7d",
    "name": "ASA de l'Ayguelongue"
  },
  {
    "id": "a2o",
    "name": "ASA de l'HENX"
  },
  {
    "id": "a6x",
    "name": "ASA de la Région de Thèze"
  },
  {
    "id": "a7c",
    "name": "ASA de la Vallée du Layza"
  },
  {
    "id": "a6g",
    "name": "ASA de LAHONTAN"
  },
  {
    "id": "a7b",
    "name": "ASA de las Garderes"
  },
  {
    "id": "a6u",
    "name": "ASA de Sarpourenx"
  },
  {
    "id": "a6w",
    "name": "ASA des Coteaux de Lagor"
  },
  {
    "id": "a6v",
    "name": "ASA des Coteaux de Sames"
  },
  {
    "id": "a2p",
    "name": "ASA du canal du BANIOU"
  },
  {
    "id": "a6n",
    "name": "ASA du LAUHIRASSE"
  },
  {
    "id": "a6o",
    "name": "ASA du Pont Long"
  },
  {
    "id": "a7f",
    "name": "ASA Itturi"
  },
  {
    "id": "u4e",
    "name": "ASAI CASTETIS"
  },
  {
    "id": "a5k",
    "name": "Association des maires et élus des collectivités de montagne ADEM64"
  },
  {
    "id": "j3k",
    "name": "Association foncière pastorale Hiru mendi"
  },
  {
    "id": "a6c",
    "name": "Association Perce Neige Pyrénées"
  },
  {
    "id": "n7e",
    "name": "Association Syndicale Autorisée ARBOSSE de ST-MICHEL/UHART-CIZE"
  },
  {
    "id": "a4y",
    "name": "Association Syndicale Autorisée d'Irrigation de Boueilh-Boueilho-Lasque"
  },
  {
    "id": "a4x",
    "name": "Association Syndicale Autorisée d'Irrigation de Josbaig"
  },
  {
    "id": "a5t",
    "name": "Association Trisomie 21 Nouvelle Aquitaine - Antenne de Pau"
  },
  {
    "id": "a4i",
    "name": "AUDAP"
  },
  {
    "id": "a1j",
    "name": "Béarnaise Habitat"
  },
  {
    "id": "m5c",
    "name": "C.C.A.S. d'ITXASSOU"
  },
  {
    "id": "n6i",
    "name": "C.I.A.S. Communauté de Communes Soule Xiberoa"
  },
  {
    "id": "k8w",
    "name": "C.I.A.S. de la communauté de communes d'ARTHEZ DE BEARN"
  },
  {
    "id": "l8b",
    "name": "C.I.A.S. SAUVETERRE DE BEARN"
  },
  {
    "id": "x6z",
    "name": "Caisse des écoles d'ANGLET"
  },
  {
    "id": "n3f",
    "name": "Caisse des Ecoles d'ESPOEY"
  },
  {
    "id": "b4v",
    "name": "Caisse des Ecoles de Bidarray"
  },
  {
    "id": "v5o",
    "name": "Caisse des Ecoles de BOUEILH-BOUEILHO-LASQUE"
  },
  {
    "id": "c6q",
    "name": "Caisse des écoles de CAMBO-LES-BAINS"
  },
  {
    "id": "z9s",
    "name": "Caisse des Ecoles de Diusse"
  },
  {
    "id": "i0t",
    "name": "Caisse des Ecoles de Garlin"
  },
  {
    "id": "t9i",
    "name": "CAISSE DES ECOLES DE MAZEROLLES"
  },
  {
    "id": "d3m",
    "name": "Caisse des écoles de SERRES-MORLAAS"
  },
  {
    "id": "k3x",
    "name": "Caisse des écoles de Vielleségure"
  },
  {
    "id": "a5r",
    "name": "CCAS Arzacq Arraziguet"
  },
  {
    "id": "z3u",
    "name": "CCAS BEYRIE-EN-BEARN"
  },
  {
    "id": "a6j",
    "name": "CCAS d'ANHAUX"
  },
  {
    "id": "y0y",
    "name": "CCAS D'ARTHEZ-D'ASSON"
  },
  {
    "id": "a1c",
    "name": "CCAS D'AUBERTIN"
  },
  {
    "id": "v7s",
    "name": "CCAS d'Estialescq"
  },
  {
    "id": "k6h",
    "name": "CCAS d'ISTURITS"
  },
  {
    "id": "n4d",
    "name": "CCAS d'UHART-CIZE"
  },
  {
    "id": "w2v",
    "name": "CCAS d''ARTIX"
  },
  {
    "id": "x2l",
    "name": "CCAS d'ANDOINS"
  },
  {
    "id": "s9j",
    "name": "CCAS d'Oloron Sainte-Marie"
  },
  {
    "id": "j2e",
    "name": "CCAS DE BESINGRAND"
  },
  {
    "id": "i0u",
    "name": "CCAS de BIDACHE"
  },
  {
    "id": "a5h",
    "name": "CCAS DE BIZANOS"
  },
  {
    "id": "a1h",
    "name": "CCAS DE BUZY"
  },
  {
    "id": "z0o",
    "name": "CCAS de CAMBO"
  },
  {
    "id": "a1q",
    "name": "CCAS DE CHERAUTE"
  },
  {
    "id": "a6r",
    "name": "CCAS de GELOS"
  },
  {
    "id": "y6t",
    "name": "CCAS de GUETHARY"
  },
  {
    "id": "r9i",
    "name": "CCAS de LARRESSORE"
  },
  {
    "id": "a4v",
    "name": "CCAS DE LASSEUBETAT"
  },
  {
    "id": "a1f",
    "name": "CCAS DE LEDEUIX"
  },
  {
    "id": "g5y",
    "name": "CCAS de MAULEON-LICHARRE"
  },
  {
    "id": "a3f",
    "name": "CCAS de MEILLON"
  },
  {
    "id": "k9z",
    "name": "CCAS de Navarrenx"
  },
  {
    "id": "q4e",
    "name": "CCAS de SAINT-PEE-SUR-NIVELLE"
  },
  {
    "id": "a3k",
    "name": "CCAS de SAINT-PIERRE-d'IRUBE"
  },
  {
    "id": "w6i",
    "name": "CCAS de SALIES-DE-BEARN"
  },
  {
    "id": "a1o",
    "name": "CCAS DE SAUVAGNON"
  },
  {
    "id": "b2s",
    "name": "CCAS de Sauvelade"
  },
  {
    "id": "u5w",
    "name": "CCAS de Serres-Castet"
  },
  {
    "id": "g6w",
    "name": "CCAS de VIODOS-ABENSE-DE-BAS"
  },
  {
    "id": "a4w",
    "name": "CCAS OUILLON"
  },
  {
    "id": "a3j",
    "name": "CE de Saint-Etienne de Baïgorry"
  },
  {
    "id": "a3i",
    "name": "CE intercommunale la région de GARLIN"
  },
  {
    "id": "f8h",
    "name": "Centre communal d'action sociale d'HENDAYE"
  },
  {
    "id": "a4m",
    "name": "Centre Communal d'Action Sociale de Balansun"
  },
  {
    "id": "j0p",
    "name": "Centre communal d'action sociale de BAYONNE"
  },
  {
    "id": "c9k",
    "name": "Centre communal d'action sociale de BOUCAU"
  },
  {
    "id": "y0d",
    "name": "Centre Communal d'Action Sociale de Ciboure"
  },
  {
    "id": "a3q",
    "name": "Centre Communal d'Action Sociale de Lasseube"
  },
  {
    "id": "t2h",
    "name": "CENTRE COMMUNAL D'ACTION SOCIALE DE NAY-BOURDETTES"
  },
  {
    "id": "w7d",
    "name": "Centre communal d'action sociale de PAU"
  },
  {
    "id": "s2a",
    "name": "Centre communal d'action sociale de PONTACQ"
  },
  {
    "id": "c0n",
    "name": "CENTRE COMMUNAL D'ACTION SOCIALE DE PORTET"
  },
  {
    "id": "a1n",
    "name": "Centre Communal d'Action Sociale de Saint Jean de Luz"
  },
  {
    "id": "h0b",
    "name": "Centre Communal d'Action Sociale d'AAST"
  },
  {
    "id": "d5a",
    "name": "Centre Communal d'Action Sociale d'ACCOUS"
  },
  {
    "id": "r8u",
    "name": "Centre communal d'action sociale d'ANGLET"
  },
  {
    "id": "p4x",
    "name": "Centre communal d'action sociale d'ARCANGUES"
  },
  {
    "id": "n0b",
    "name": "Centre Communal d'Action Sociale d'AREN"
  },
  {
    "id": "g9n",
    "name": "Centre Communal d'Action Sociale d'ARESSY"
  },
  {
    "id": "j7m",
    "name": "Centre communal d'action sociale d'ARGAGNON"
  },
  {
    "id": "k0d",
    "name": "Centre communal d'action sociale d'ARGELOS"
  },
  {
    "id": "x9z",
    "name": "Centre communal d'action sociale d'ARUDY"
  },
  {
    "id": "n6z",
    "name": "Centre communal d'action sociale d'ARZACQ-ARRAZIGUET"
  },
  {
    "id": "w3f",
    "name": "Centre Communal d'Action Sociale d'ASCAIN"
  },
  {
    "id": "y0m",
    "name": "Centre communal d'action sociale d'ASSAT"
  },
  {
    "id": "x2n",
    "name": "Centre Communal d'Action Sociale d'ASSON"
  },
  {
    "id": "k9x",
    "name": "Centre Communal d'Action sociale d'ASTIS"
  },
  {
    "id": "v5c",
    "name": "Centre Communal d'Action Sociale d'AUBIN"
  },
  {
    "id": "b4i",
    "name": "Centre Communal d'Action Sociale d'AUBOUS"
  },
  {
    "id": "q4t",
    "name": "Centre communal d'action sociale d'ESPELETTE"
  },
  {
    "id": "g7b",
    "name": "Centre Communal d'Action Sociale d'ESPOEY"
  },
  {
    "id": "h1a",
    "name": "Centre communal d'action sociale d'IGON"
  },
  {
    "id": "e7t",
    "name": "Centre Communal d'Action Sociale d'ISPOURE"
  },
  {
    "id": "d9r",
    "name": "Centre Communal d'Action Sociale d'OGENNE-CAMPTORT"
  },
  {
    "id": "s7z",
    "name": "Centre communal d'action sociale d'OGEU-LES-BAINS"
  },
  {
    "id": "u2c",
    "name": "Centre Communal d'Action Sociale d'ORIN"
  },
  {
    "id": "f8y",
    "name": "Centre communal d'action sociale d'ORTHEZ"
  },
  {
    "id": "s9h",
    "name": "Centre Communal d'Action Sociale d'OSSE-EN-ASPE"
  },
  {
    "id": "q9m",
    "name": "Centre Communal d'Action Sociale d'URRUGNE"
  },
  {
    "id": "x7s",
    "name": "Centre communal d'action sociale d'URT"
  },
  {
    "id": "x8j",
    "name": "Centre communal d'action sociale d'USTARITZ"
  },
  {
    "id": "i6r",
    "name": "Centre Communal d'Action Sociale d'UZEIN"
  },
  {
    "id": "k7y",
    "name": "Centre communal d'action sociale de BAIGTS-DE-BEARN"
  },
  {
    "id": "j3z",
    "name": "Centre communal d'action sociale de BARZUN"
  },
  {
    "id": "s4r",
    "name": "Centre communal d'action sociale de BAUDREIX"
  },
  {
    "id": "o6j",
    "name": "Centre communal d'action sociale de BENEJACQ"
  },
  {
    "id": "z6x",
    "name": "Centre communal d'action sociale de BERENX"
  },
  {
    "id": "w2d",
    "name": "Centre Communal d'Action Sociale de BIARRITZ"
  },
  {
    "id": "h7q",
    "name": "Centre Communal d'Action Sociale de BIDART"
  },
  {
    "id": "t8c",
    "name": "Centre Communal d'Action Sociale de BILLERE"
  },
  {
    "id": "j3u",
    "name": "Centre communal d'action sociale de BIRON"
  },
  {
    "id": "m5d",
    "name": "Centre communal d'action sociale de BOEIL-BEZING"
  },
  {
    "id": "m4y",
    "name": "Centre Communal d'Action Sociale de BONNUT"
  },
  {
    "id": "r3o",
    "name": "Centre Communal d'Action Sociale de BORDES"
  },
  {
    "id": "k1d",
    "name": "Centre Communal d'Action Sociale de BOUEILH-BOUEILHO-LASQUE"
  },
  {
    "id": "u2z",
    "name": "Centre communal d'action sociale de Briscous"
  },
  {
    "id": "j4p",
    "name": "Centre communal d'action sociale de Bugnein"
  },
  {
    "id": "k9g",
    "name": "Centre communal d'action sociale de BUNUS"
  },
  {
    "id": "h2h",
    "name": "Centre communal d'action sociale de BUROSSE-MENDOUSSE"
  },
  {
    "id": "x6l",
    "name": "Centre communal d'action sociale de CASTEIDE-CANDAU"
  },
  {
    "id": "a3c",
    "name": "Centre communal d'action sociale de CASTETNER"
  },
  {
    "id": "s9y",
    "name": "Centre Communal d'Action Sociale de CASTETPUGON"
  },
  {
    "id": "y1q",
    "name": "Centre Communal d'Action Sociale de CONCHEZ-DE-BEARN"
  },
  {
    "id": "s0y",
    "name": "Centre Communal d'Action Sociale de CUQUERON"
  },
  {
    "id": "f7w",
    "name": "Centre communal d'action sociale de DOAZON"
  },
  {
    "id": "i5z",
    "name": "Centre communal d'action sociale de GARLIN"
  },
  {
    "id": "p9c",
    "name": "Centre Communal d'Action Sociale de GAYON"
  },
  {
    "id": "g2f",
    "name": "Centre Communal d'Action Sociale de GEUS-D'OLORON"
  },
  {
    "id": "o6m",
    "name": "Centre Communal d'Action Sociale de GURS"
  },
  {
    "id": "m9t",
    "name": "Centre communal d'action sociale de HALSOU"
  },
  {
    "id": "p8x",
    "name": "Centre communal d'action sociale de JATXOU"
  },
  {
    "id": "c2w",
    "name": "Centre Communal d'Action Sociale de JAXU"
  },
  {
    "id": "m6a",
    "name": "CENTRE COMMUNAL D'ACTION SOCIALE DE LAA-MONDRANS"
  },
  {
    "id": "q6t",
    "name": "centre communal d'action sociale de Labastide Monréjeau"
  },
  {
    "id": "m6r",
    "name": "Centre communal d'action sociale de LABASTIDE-CEZERACQ"
  },
  {
    "id": "l8v",
    "name": "Centre Communal d'Action Sociale de LABEYRIE"
  },
  {
    "id": "v3r",
    "name": "Centre Communal d'Action Sociale de LACADEE"
  },
  {
    "id": "a3g",
    "name": "Centre communal d'action sociale de LANNEPLAA"
  },
  {
    "id": "w1d",
    "name": "Centre communal d'action sociale de LAROIN"
  },
  {
    "id": "g5z",
    "name": "Centre communal d'action sociale de LEREN"
  },
  {
    "id": "s3r",
    "name": "Centre communal d'action sociale de LESCAR"
  },
  {
    "id": "b0o",
    "name": "CENTRE COMMUNAL D'ACTION SOCIALE DE LESTELLE-BETHARRAM"
  },
  {
    "id": "x2d",
    "name": "Centre communal d'action sociale de LIMENDOUS"
  },
  {
    "id": "t2q",
    "name": "Centre communal d'action sociale de LONS"
  },
  {
    "id": "o3a",
    "name": "Centre communal d'action sociale de LOURENTIES"
  },
  {
    "id": "f1h",
    "name": "Centre Communal d'Action Sociale de LUCGARIER"
  },
  {
    "id": "y3d",
    "name": "Centre Communal d'Action Sociale de LUCQ-DE-BEARN"
  },
  {
    "id": "u3b",
    "name": "Centre Communal d'Action Sociale de MASCARAAS-HARON"
  },
  {
    "id": "a5n",
    "name": "Centre communal d'action sociale de MAZEROLLES"
  },
  {
    "id": "s2d",
    "name": "Centre communal d'action sociale de MERACQ"
  },
  {
    "id": "z7x",
    "name": "Centre Communal d'Action Sociale de MONCLA"
  },
  {
    "id": "d7j",
    "name": "Centre communal d'action sociale de MONEIN"
  },
  {
    "id": "x3v",
    "name": "Centre communal d'action sociale de MONT"
  },
  {
    "id": "p1w",
    "name": "Centre communal d'action sociale de MONTANER"
  },
  {
    "id": "o1l",
    "name": "Centre communal d'action sociale de Morlaas"
  },
  {
    "id": "m8u",
    "name": "Centre Communal d'Action Sociale de MOUGUERRE"
  },
  {
    "id": "v0l",
    "name": "Centre Communal d'Action Sociale de MOURENX"
  },
  {
    "id": "w4x",
    "name": "Centre communal d'action sociale de NARCASTET"
  },
  {
    "id": "b9q",
    "name": "Centre communal d'action sociale de NAVAILLES-ANGOS"
  },
  {
    "id": "m1w",
    "name": "Centre communal d'action sociale de POEY-DE-LESCAR"
  },
  {
    "id": "v7n",
    "name": "Centre Communal d'Action Sociale de PRECHACQ-JOSBAIG"
  },
  {
    "id": "t5r",
    "name": "Centre Communal d'Action Sociale de PRECHACQ-NAVARRENX"
  },
  {
    "id": "s2h",
    "name": "Centre communal d'action sociale de RONTIGNON"
  },
  {
    "id": "q2k",
    "name": "Centre communal d'action sociale de SAINT-ABIT"
  },
  {
    "id": "a6q",
    "name": "Centre Communal d'Action Sociale de SAINT-BOES"
  },
  {
    "id": "m6w",
    "name": "Centre Communal d'Action Sociale de Saint-Etienne-de-Baigorry"
  },
  {
    "id": "j0e",
    "name": "Centre Communal d'Action Sociale de SAINT-GIRONS-EN-BEARN"
  },
  {
    "id": "s6x",
    "name": "Centre Communal d'Action Sociale de SAINT-JEAN-POUDGE"
  },
  {
    "id": "j3j",
    "name": "Centre Communal d'Action Sociale de SAINT-MICHEL"
  },
  {
    "id": "f4x",
    "name": "Centre communal d'action sociale de SAINT-PE-DE-LEREN"
  },
  {
    "id": "a7p",
    "name": "Centre communal d'action sociale de SALLES-MONGISCARD"
  },
  {
    "id": "u4x",
    "name": "Centre Communal d'Action Sociale de SARPOURENX"
  },
  {
    "id": "y4p",
    "name": "Centre Communal d'Action Sociale de SAUCEDE"
  },
  {
    "id": "x6t",
    "name": "Centre communal d'action sociale de SEBY"
  },
  {
    "id": "h2y",
    "name": "Centre communal d'action sociale de SERRES-MORLAAS"
  },
  {
    "id": "h8d",
    "name": "Centre communal d'action sociale de SERRES-SAINTE-MARIE"
  },
  {
    "id": "x6h",
    "name": "Centre Communal d'Action Sociale de SIROS"
  },
  {
    "id": "f3q",
    "name": "Centre Communal d'Action Sociale de SOURAIDE"
  },
  {
    "id": "p0s",
    "name": "Centre Communal d'Action Sociale de TADOUSSE-USSAU"
  },
  {
    "id": "n8r",
    "name": "Centre communal d'action sociale de Vielleségure"
  },
  {
    "id": "r3f",
    "name": "Centre de gestion des Pyrénées-Atlantiques"
  },
  {
    "id": "h6m",
    "name": "Centre Intercommunal d'Action Sociale du Pays de BIDACHE"
  },
  {
    "id": "t7f",
    "name": "Chambre d'agriculture des Pyrénées-Atlantiques"
  },
  {
    "id": "a1l",
    "name": "CIAS Pays Basque"
  },
  {
    "id": "r0b",
    "name": "CIAS Syndicat intercommunal d'Arhez-de-Béarn"
  },
  {
    "id": "l1b",
    "name": "Collège de MONEIN"
  },
  {
    "id": "a9j",
    "name": "Collège Les Cinq Monts de Laruns"
  },
  {
    "id": "f6b",
    "name": "Collège Marguerite de Navarre"
  },
  {
    "id": "y3z",
    "name": "Collège René Forgues de Serres-Castet"
  },
  {
    "id": "a4u",
    "name": "Commission Syndicale de Bielle et Bilhères"
  },
  {
    "id": "p0r",
    "name": "Commission syndicale de l'OSTABARET"
  },
  {
    "id": "m4v",
    "name": "Commission syndicale de la vallée de BAIGORRI"
  },
  {
    "id": "a4n",
    "name": "Commission Syndicale du Bois de Mixe"
  },
  {
    "id": "n3r",
    "name": "Commission syndicale du Haut Ossau"
  },
  {
    "id": "e2o",
    "name": "Commission syndicale du PAYS DE CIZE"
  },
  {
    "id": "l9g",
    "name": "Commission syndicale du pays de Soule"
  },
  {
    "id": "v8g",
    "name": "Commission syndicale PARBAYSE CUQUERON"
  },
  {
    "id": "v6k",
    "name": "Commission syndicale pour la gestion de la donation Bur"
  },
  {
    "id": "i5g",
    "name": "Communauté d'agglomération PAU BEARN PYRENEES"
  },
  {
    "id": "a3v",
    "name": "Communauté d'agglomération Pays basque"
  },
  {
    "id": "q9t",
    "name": "Communauté d'Agglomération Sud Pays Basque"
  },
  {
    "id": "a4j",
    "name": "Communauté de Communes Adour Madiran"
  },
  {
    "id": "r0i",
    "name": "Communauté de communes d'AMIKUZE"
  },
  {
    "id": "u7t",
    "name": "Communauté de communes d'ARTHEZ-DE-BEARN"
  },
  {
    "id": "z8a",
    "name": "Communauté de communes de JOSBAIG"
  },
  {
    "id": "c4h",
    "name": "Communauté de communes de la vallée d'Aspe"
  },
  {
    "id": "j6f",
    "name": "Communauté de communes de la Vallée d'Ossau"
  },
  {
    "id": "k0t",
    "name": "Communauté de communes de la Vallée de Barétous"
  },
  {
    "id": "a1z",
    "name": "Communauté de communes de LACQ"
  },
  {
    "id": "t5b",
    "name": "Communauté de communes de LACQ-ORTHEZ"
  },
  {
    "id": "i8k",
    "name": "Communauté de communes de LAGOR"
  },
  {
    "id": "i5c",
    "name": "Communauté de communes de MONEIN"
  },
  {
    "id": "m1r",
    "name": "Communauté de Communes de SALIES-DE-BEARN"
  },
  {
    "id": "b2g",
    "name": "Communauté de communes de SAUVETERRE-DE-BEARN"
  },
  {
    "id": "b5r",
    "name": "Communauté de communes de SOULE-XIBEROA"
  },
  {
    "id": "x8r",
    "name": "Communauté de communes de Thèze"
  },
  {
    "id": "t1e",
    "name": "Communauté de communes des Luys en Béarn"
  },
  {
    "id": "a3o",
    "name": "COMMUNAUTE DE COMMUNES DES LUYS EN BEARN"
  },
  {
    "id": "a3s",
    "name": "Communauté de communes du BEARN DES GAVES"
  },
  {
    "id": "d0q",
    "name": "Communauté de communes du canton d'ARZACQ"
  },
  {
    "id": "m8x",
    "name": "Communauté de Communes du Canton d'ORTHEZ"
  },
  {
    "id": "g4v",
    "name": "Communauté de communes du canton de Garlin"
  },
  {
    "id": "w5u",
    "name": "Communauté de Communes du Canton de Lembeye en Vic-Bilh"
  },
  {
    "id": "a2t",
    "name": "Communauté de Communes du Haut Béarn"
  },
  {
    "id": "w5k",
    "name": "Communauté de communes du Luy de Béarn"
  },
  {
    "id": "s3h",
    "name": "Communauté de communes du MIEY de BEARN"
  },
  {
    "id": "k7o",
    "name": "Communauté de communes du NORD EST BEARN"
  },
  {
    "id": "l6q",
    "name": "Communauté de communes du PAYS d'HASPARREN"
  },
  {
    "id": "s3d",
    "name": "Communauté de communes du PAYS de BIDACHE"
  },
  {
    "id": "d6g",
    "name": "Communauté de communes du Pays de Morlaàs"
  },
  {
    "id": "s6o",
    "name": "Communauté de communes du Pays de Nay"
  },
  {
    "id": "b0l",
    "name": "Communauté de communes du Piémont Oloronais"
  },
  {
    "id": "l9f",
    "name": "Communauté de communes ERROBI"
  },
  {
    "id": "c7y",
    "name": "Communauté de communes GARAZI BAIGORRI"
  },
  {
    "id": "r2j",
    "name": "Communauté de communes GAVE et COTEAUX"
  },
  {
    "id": "j5r",
    "name": "Communauté de communes IHOLDI-OZTIBARRE"
  },
  {
    "id": "i6g",
    "name": "Communauté de communes NIVE-ADOUR"
  },
  {
    "id": "f8s",
    "name": "Communauté de communes SUD PAYS BASQUE"
  },
  {
    "id": "g1u",
    "name": "Communauté de communesdu Canton de NAVARRENX"
  },
  {
    "id": "e8l",
    "name": "Communauté des communes OUSSE-GABAS"
  },
  {
    "id": "c6k",
    "name": "Commune associée de SAINTE-SUZANNE"
  },
  {
    "id": "t4q",
    "name": "commune d 'Ascain"
  },
  {
    "id": "f8j",
    "name": "Commune d'ABERE"
  },
  {
    "id": "t0b",
    "name": "Commune d'ABIDOS"
  },
  {
    "id": "a5b",
    "name": "Commune d'Abitain"
  },
  {
    "id": "w7v",
    "name": "Commune d'AÏCIRITS-CAMOU-SUHAST"
  },
  {
    "id": "f8z",
    "name": "Commune d'AINCILLE"
  },
  {
    "id": "g0o",
    "name": "Commune d'AINHARP"
  },
  {
    "id": "q2n",
    "name": "Commune d'AINHICE-MONGELOS"
  },
  {
    "id": "k8r",
    "name": "Commune d'ALOS-SIBAS-ABENSE"
  },
  {
    "id": "a3m",
    "name": "Commune d'AMENDEUIX-ONEIX"
  },
  {
    "id": "a3u",
    "name": "Commune d'ANCE FEAS"
  },
  {
    "id": "h5r",
    "name": "Commune d'ANDREIN"
  },
  {
    "id": "d6v",
    "name": "Commune d'ANGOUS"
  },
  {
    "id": "a5s",
    "name": "Commune d'Anhaux"
  },
  {
    "id": "k4c",
    "name": "Commune d'ARAMITS"
  },
  {
    "id": "v3c",
    "name": "COMMUNE D'ARAUX"
  },
  {
    "id": "e6n",
    "name": "Commune d'ARBERATS-SILLEGUE"
  },
  {
    "id": "d5o",
    "name": "Commune d'Arbonne"
  },
  {
    "id": "w6w",
    "name": "Commune d'ARBUS"
  },
  {
    "id": "u1h",
    "name": "Commune d'ARESSY"
  },
  {
    "id": "i9u",
    "name": "Commune d'ARETTE"
  },
  {
    "id": "n0z",
    "name": "Commune d'ARGELOS"
  },
  {
    "id": "x6p",
    "name": "Commune d'ARMENDARITS"
  },
  {
    "id": "w6x",
    "name": "Commune d'ARNEGUY"
  },
  {
    "id": "o3z",
    "name": "Commune d'ARRAUTE-CHARRITTE"
  },
  {
    "id": "c4i",
    "name": "Commune d'ARTHEZ-D'ASSON"
  },
  {
    "id": "v7u",
    "name": "Commune d'ARTIX"
  },
  {
    "id": "k3c",
    "name": "Commune d'ARUDY"
  },
  {
    "id": "p5q",
    "name": "Commune d'ARZACQ-ARRAZIGUET"
  },
  {
    "id": "n2c",
    "name": "commune d'Asasp-Arros"
  },
  {
    "id": "w0l",
    "name": "Commune d'ASTE-BEON"
  },
  {
    "id": "f5r",
    "name": "Commune d'AUGA"
  },
  {
    "id": "j4z",
    "name": "Commune d'AUSSEVIELLE"
  },
  {
    "id": "c5h",
    "name": "Commune d'AUSSURUCQ"
  },
  {
    "id": "i3d",
    "name": "Commune d'ESCURES"
  },
  {
    "id": "m7s",
    "name": "Commune d'ESLOURENTIES"
  },
  {
    "id": "h7k",
    "name": "Commune d'ESPECHEDE"
  },
  {
    "id": "w7a",
    "name": "Commune d'ESPIUTE"
  },
  {
    "id": "i3h",
    "name": "Commune d'Estialescq"
  },
  {
    "id": "i7p",
    "name": "Commune d'ESTOS"
  },
  {
    "id": "d3s",
    "name": "Commune d'ETCHARRY"
  },
  {
    "id": "m8j",
    "name": "Commune d'EYSUS"
  },
  {
    "id": "a5l",
    "name": "Commune d'Haux"
  },
  {
    "id": "o4q",
    "name": "Commune d'HELETTE"
  },
  {
    "id": "s7s",
    "name": "Commune d'HERRERE"
  },
  {
    "id": "g4c",
    "name": "Commune d'HIGUERES-SOUYE"
  },
  {
    "id": "a7i",
    "name": "Commune d'IDRON"
  },
  {
    "id": "r7s",
    "name": "Commune d'IHOLDY"
  },
  {
    "id": "b7r",
    "name": "Commune d'Issor"
  },
  {
    "id": "g8j",
    "name": "Commune d'ITXASSOU"
  },
  {
    "id": "u9a",
    "name": "Commune d'OGENNE-CAMPTORT"
  },
  {
    "id": "z8p",
    "name": "Commune d'ORIN"
  },
  {
    "id": "o9e",
    "name": "Commune d'ORSANCO"
  },
  {
    "id": "i4v",
    "name": "Commune d'OS-MARSILLON"
  },
  {
    "id": "c0m",
    "name": "Commune d'OSSAS-SUHARE"
  },
  {
    "id": "i2m",
    "name": "Commune d'OSSE-EN-ASPE"
  },
  {
    "id": "x7a",
    "name": "Commune d'OSSENX"
  },
  {
    "id": "w8l",
    "name": "Commune d'OSTABAT-ASME"
  },
  {
    "id": "c9v",
    "name": "Commune d'OUILLON"
  },
  {
    "id": "k1p",
    "name": "Commune d'OUSSE"
  },
  {
    "id": "m4t",
    "name": "Commune d'UHART-CIZE"
  },
  {
    "id": "r5a",
    "name": "Commune d'URCUIT"
  },
  {
    "id": "m1z",
    "name": "Commune d'URDOS"
  },
  {
    "id": "t5s",
    "name": "Commune d'URRUGNE"
  },
  {
    "id": "w4f",
    "name": "Commune d'USTARITZ"
  },
  {
    "id": "j7w",
    "name": "Commune d'UZEIN"
  },
  {
    "id": "b3e",
    "name": "Commune d'AAST"
  },
  {
    "id": "t8h",
    "name": "Commune d'ABOS"
  },
  {
    "id": "g1h",
    "name": "Commune d'ACCOUS"
  },
  {
    "id": "z3k",
    "name": "Commune d'AGNOS"
  },
  {
    "id": "y8h",
    "name": "Commune d'Ahaxe-Alciette-Bascassan"
  },
  {
    "id": "r0p",
    "name": "Commune d'AHETZE"
  },
  {
    "id": "a4g",
    "name": "Commune d'AINHOA"
  },
  {
    "id": "u8o",
    "name": "Commune d'ALCAY-ALCABEHETY-SUNHARETTE"
  },
  {
    "id": "x0n",
    "name": "Commune d'AMOROTS-SUCCOS"
  },
  {
    "id": "v0i",
    "name": "Commune d'ANDOINS"
  },
  {
    "id": "k2l",
    "name": "Commune d'ANGAIS"
  },
  {
    "id": "t3f",
    "name": "Commune d'ANGLET"
  },
  {
    "id": "m2f",
    "name": "Commune d'ANOS"
  },
  {
    "id": "s6r",
    "name": "Commune d'ANOYE"
  },
  {
    "id": "d8j",
    "name": "Commune d'ARAUJUZON"
  },
  {
    "id": "n8a",
    "name": "Commune d'ARBOUET-SUSSAUTE"
  },
  {
    "id": "s3i",
    "name": "Commune d'ARCANGUES"
  },
  {
    "id": "x7c",
    "name": "Commune d'AREN"
  },
  {
    "id": "q8y",
    "name": "Commune d'ARGAGNON"
  },
  {
    "id": "x0u",
    "name": "Commune d'ARGET"
  },
  {
    "id": "d2q",
    "name": "Commune d'ARHANSUS"
  },
  {
    "id": "j6y",
    "name": "Commune d'ARNOS"
  },
  {
    "id": "n9a",
    "name": "Commune d'AROUE-ITHORROTS-OLHAIBY"
  },
  {
    "id": "x4t",
    "name": "Commune d'ARRAST-LARREBIEU"
  },
  {
    "id": "a2x",
    "name": "Commune d'Arricau-Bordes"
  },
  {
    "id": "z1h",
    "name": "Commune d'ARRIEN"
  },
  {
    "id": "w1t",
    "name": "Commune d'ARROS-DE-NAY"
  },
  {
    "id": "f8l",
    "name": "Commune d'ARROSES"
  },
  {
    "id": "o6a",
    "name": "Commune d'ARTHEZ-DE-BEARN"
  },
  {
    "id": "o2t",
    "name": "Commune d'ARTIGUELOUTAN"
  },
  {
    "id": "y8j",
    "name": "Commune d'ARTIGUELOUVE"
  },
  {
    "id": "h9v",
    "name": "Commune d'ASCARAT"
  },
  {
    "id": "e8g",
    "name": "Commune d'ASSAT"
  },
  {
    "id": "z8m",
    "name": "Commune d'ASSON"
  },
  {
    "id": "c6h",
    "name": "Commune d'ASTIS"
  },
  {
    "id": "f8p",
    "name": "Commune d'ATHOS-ASPIS"
  },
  {
    "id": "g0n",
    "name": "Commune d'AUBERTIN"
  },
  {
    "id": "y6m",
    "name": "Commune d'AUBIN"
  },
  {
    "id": "g6r",
    "name": "Commune d'AUBOUS"
  },
  {
    "id": "d9l",
    "name": "Commune d'AUDAUX"
  },
  {
    "id": "g0u",
    "name": "Commune d'AURIAC"
  },
  {
    "id": "d9i",
    "name": "Commune d'AURIONS-IDERNES"
  },
  {
    "id": "k1i",
    "name": "Commune d'AUTERRIVE"
  },
  {
    "id": "c9n",
    "name": "Commune d'AUTEVIELLE"
  },
  {
    "id": "f1r",
    "name": "Commune d'AYDIE"
  },
  {
    "id": "s7e",
    "name": "Commune d'AYDIUS"
  },
  {
    "id": "g7e",
    "name": "Commune d'AYHERRE"
  },
  {
    "id": "d9k",
    "name": "Commune d'Escos"
  },
  {
    "id": "m4g",
    "name": "Commune d'ESCOT"
  },
  {
    "id": "b9n",
    "name": "COMMUNE D'ESCOU"
  },
  {
    "id": "m5u",
    "name": "Commune d'ESCOUBES"
  },
  {
    "id": "k4f",
    "name": "Commune d'ESCOUT"
  },
  {
    "id": "o2n",
    "name": "Commune d'ESPELETTE"
  },
  {
    "id": "m1m",
    "name": "Commune d'ESPES-UNDUREIN"
  },
  {
    "id": "b9g",
    "name": "Commune d'ESPOEY"
  },
  {
    "id": "z3p",
    "name": "Commune d'ESQUIULE"
  },
  {
    "id": "h7u",
    "name": "Commune d'ESTERENCUBY"
  },
  {
    "id": "e7e",
    "name": "Commune d'ETCHEBAR"
  },
  {
    "id": "z4z",
    "name": "Commune d'ETSAUT"
  },
  {
    "id": "u4v",
    "name": "Commune d'HAGETAUBIN"
  },
  {
    "id": "a4a",
    "name": "Commune d'HENDAYE"
  },
  {
    "id": "b5l",
    "name": "Commune d'HOSTA"
  },
  {
    "id": "f1m",
    "name": "Commune d'IBAROLLE"
  },
  {
    "id": "q7f",
    "name": "Commune d'IDAUX-MENDY"
  },
  {
    "id": "y6r",
    "name": "Commune d'IGON"
  },
  {
    "id": "c9d",
    "name": "Commune d'ILHARRE"
  },
  {
    "id": "r6n",
    "name": "Commune d'IRISSARRY"
  },
  {
    "id": "g1x",
    "name": "Commune d'IROULEGUY"
  },
  {
    "id": "i1c",
    "name": "commune d'Iseste"
  },
  {
    "id": "j8a",
    "name": "Commune d'ISPOURE"
  },
  {
    "id": "h7r",
    "name": "Commune d'ISTURITS"
  },
  {
    "id": "x5h",
    "name": "Commune d'OGEU-LES-BAINS"
  },
  {
    "id": "s3x",
    "name": "Commune d'Oloron-Sainte-Marie"
  },
  {
    "id": "p1v",
    "name": "Commune d'ORAAS"
  },
  {
    "id": "f0z",
    "name": "Commune d'ORDIARP"
  },
  {
    "id": "b6s",
    "name": "Commune d'OREGUE"
  },
  {
    "id": "c7q",
    "name": "Commune d'ORION"
  },
  {
    "id": "s5z",
    "name": "Commune d'ORRIULE"
  },
  {
    "id": "n5m",
    "name": "Commune d'ORTHEZ"
  },
  {
    "id": "i7o",
    "name": "commune d'Osserain-Rivareyte"
  },
  {
    "id": "a6y",
    "name": "Commune d'Osses"
  },
  {
    "id": "q2e",
    "name": "Commune d'OZENX-MONTESTRUCQ"
  },
  {
    "id": "o8h",
    "name": "Commune d'UHART-MIXE"
  },
  {
    "id": "e8r",
    "name": "Commune d'URDES"
  },
  {
    "id": "g5c",
    "name": "Commune d'UREPEL"
  },
  {
    "id": "a8a",
    "name": "Commune d'UROST"
  },
  {
    "id": "u6c",
    "name": "Commune d'UZAN"
  },
  {
    "id": "s0w",
    "name": "Commune d'UZOS"
  },
  {
    "id": "w4a",
    "name": "Commune de  LABETS-BISCAY"
  },
  {
    "id": "s5i",
    "name": "Commune de ANCE"
  },
  {
    "id": "z5e",
    "name": "Commune de ARANCOU"
  },
  {
    "id": "u9m",
    "name": "Commune de BAIGTS-DE-BEARN"
  },
  {
    "id": "a3w",
    "name": "Commune de BALANSUN"
  },
  {
    "id": "b1e",
    "name": "Commune de BALEIX"
  },
  {
    "id": "v9k",
    "name": "Commune de BALIRACQ-MAUMUSSON"
  },
  {
    "id": "m3w",
    "name": "Commune de BANCA"
  },
  {
    "id": "c6v",
    "name": "Commune de BARCUS"
  },
  {
    "id": "z2b",
    "name": "Commune de BARDOS"
  },
  {
    "id": "i4t",
    "name": "Commune de BARINQUE"
  },
  {
    "id": "h9r",
    "name": "Commune de BARRAUTE-CAMU"
  },
  {
    "id": "e2f",
    "name": "Commune de BARZUN"
  },
  {
    "id": "u2v",
    "name": "Commune de BASSILLON-VAUZE"
  },
  {
    "id": "a1u",
    "name": "Commune de Bassussarry"
  },
  {
    "id": "t4n",
    "name": "Commune de BASTANES"
  },
  {
    "id": "v2r",
    "name": "Commune de BAUDREIX"
  },
  {
    "id": "i0r",
    "name": "Commune de BAYONNE"
  },
  {
    "id": "u4p",
    "name": "Commune de BEDOUS"
  },
  {
    "id": "w3t",
    "name": "Commune de BEGUIOS"
  },
  {
    "id": "z6b",
    "name": "Commune de BEHASQUE-LAPISTE"
  },
  {
    "id": "c3c",
    "name": "Commune de BEHORLEGUY"
  },
  {
    "id": "h4l",
    "name": "Commune de BELLOCQ"
  },
  {
    "id": "h0d",
    "name": "Commune de BENEJACQ"
  },
  {
    "id": "a6z",
    "name": "Commune de BENTAYOU-SEREE"
  },
  {
    "id": "h1c",
    "name": "Commune de BEOST"
  },
  {
    "id": "z7u",
    "name": "Commune de BERENX"
  },
  {
    "id": "h5j",
    "name": "Commune de BERGOUEY-VIELLENAVE"
  },
  {
    "id": "k2w",
    "name": "commune de Bernadets"
  },
  {
    "id": "u7u",
    "name": "Commune de BERROGAIN-LARUNS"
  },
  {
    "id": "f8u",
    "name": "Commune de BESCAT"
  },
  {
    "id": "s5d",
    "name": "Commune de BESINGRAND"
  },
  {
    "id": "y2j",
    "name": "Commune de BETRACQ"
  },
  {
    "id": "i2b",
    "name": "Commune de BEUSTE"
  },
  {
    "id": "l6e",
    "name": "Commune de BEYRIE-EN-BEARN"
  },
  {
    "id": "d8z",
    "name": "Commune de BEYRIE-SUR-JOYEUSE"
  },
  {
    "id": "u2y",
    "name": "Commune de BIARRITZ"
  },
  {
    "id": "r8t",
    "name": "Commune de BIDACHE"
  },
  {
    "id": "h7h",
    "name": "Commune de BIDARRAY"
  },
  {
    "id": "u9g",
    "name": "Commune de BIDART"
  },
  {
    "id": "b3h",
    "name": "Commune de BIDOS"
  },
  {
    "id": "k8k",
    "name": "Commune de BIELLE"
  },
  {
    "id": "g9h",
    "name": "Commune de Bilhères"
  },
  {
    "id": "i6t",
    "name": "Commune de BILLERE"
  },
  {
    "id": "a1w",
    "name": "Commune de BIRIATOU"
  },
  {
    "id": "u9j",
    "name": "Commune de BIRON"
  },
  {
    "id": "s8u",
    "name": "Commune de BIZANOS"
  },
  {
    "id": "o0v",
    "name": "Commune de BOEIL-BEZING"
  },
  {
    "id": "b2d",
    "name": "Commune de BONLOC"
  },
  {
    "id": "e5w",
    "name": "Commune de BONNUT"
  },
  {
    "id": "q1q",
    "name": "COMMUNE DE BORCE"
  },
  {
    "id": "u6a",
    "name": "Commune de BORDERES"
  },
  {
    "id": "f8g",
    "name": "Commune de BORDES"
  },
  {
    "id": "f4h",
    "name": "Commune de BOSDARROS"
  },
  {
    "id": "l2w",
    "name": "Commune de BOUCAU"
  },
  {
    "id": "j8q",
    "name": "Commune de BOUEILH-BOUEILHO-LASQUE"
  },
  {
    "id": "e6e",
    "name": "Commune de BOUGARBER"
  },
  {
    "id": "l2e",
    "name": "Commune de BOUILLON"
  },
  {
    "id": "v6j",
    "name": "Commune de Boumourt"
  },
  {
    "id": "d4i",
    "name": "Commune de BOURDETTES"
  },
  {
    "id": "g0t",
    "name": "Commune de BOURNOS"
  },
  {
    "id": "z9c",
    "name": "Commune de BRISCOUS"
  },
  {
    "id": "y6e",
    "name": "Commune de BRUGES-CAPBIS-MIFAGET"
  },
  {
    "id": "w6c",
    "name": "Commune de BUGNEIN"
  },
  {
    "id": "j0v",
    "name": "Commune de BUNUS"
  },
  {
    "id": "w0j",
    "name": "Commune de BURGARONNE"
  },
  {
    "id": "v9m",
    "name": "Commune de BUROS"
  },
  {
    "id": "d7r",
    "name": "Commune de BUROSSE-MENDOUSSE"
  },
  {
    "id": "d7p",
    "name": "Commune de BUSSUNARITS-SARRASQUETTE"
  },
  {
    "id": "a4q",
    "name": "Commune de BUSTINCE-IRIBERRY"
  },
  {
    "id": "z0s",
    "name": "Commune de BUZIET"
  },
  {
    "id": "z5r",
    "name": "Commune de BUZY"
  },
  {
    "id": "l1l",
    "name": "Commune de CABIDOS"
  },
  {
    "id": "f7e",
    "name": "Commune de Cadillon"
  },
  {
    "id": "k0n",
    "name": "Commune de CAMBO-LES-BAINS"
  },
  {
    "id": "y6u",
    "name": "Commune de CAME"
  },
  {
    "id": "e0b",
    "name": "Commune de CAMOU-CIHIGUE"
  },
  {
    "id": "e0l",
    "name": "Commune de CARDESSE"
  },
  {
    "id": "f5h",
    "name": "Commune de ÇARO"
  },
  {
    "id": "a2j",
    "name": "Commune de CARRERE"
  },
  {
    "id": "p3m",
    "name": "Commune de CARRESSE-CASSABER"
  },
  {
    "id": "t1r",
    "name": "Commune de CASTAGNEDE"
  },
  {
    "id": "e6v",
    "name": "Commune de CASTEIDE-CAMI"
  },
  {
    "id": "k2g",
    "name": "Commune de CASTEIDE-CANDAU"
  },
  {
    "id": "y6n",
    "name": "Commune de CASTEIDE-DOAT"
  },
  {
    "id": "l7w",
    "name": "COMMUNE DE CASTERA_LOUBIX"
  },
  {
    "id": "w4g",
    "name": "Commune de CASTET"
  },
  {
    "id": "t7b",
    "name": "Commune de CASTETBON"
  },
  {
    "id": "i1t",
    "name": "Commune de CASTETIS"
  },
  {
    "id": "z9i",
    "name": "COMMUNE DE CASTETNAU-CAMBLONG"
  },
  {
    "id": "v3s",
    "name": "Commune de CASTETNER"
  },
  {
    "id": "n1e",
    "name": "Commune de CASTETPUGON"
  },
  {
    "id": "f2u",
    "name": "Commune de CASTILLON d'ARTHEZ-DE-BEARN"
  },
  {
    "id": "g8e",
    "name": "Commune de CASTILLON DE LEMBEYE"
  },
  {
    "id": "t5m",
    "name": "Commune de CAUBIOS-LOOS"
  },
  {
    "id": "p3l",
    "name": "Commune de CESCAU"
  },
  {
    "id": "k7l",
    "name": "Commune de CETTE-EYGUN"
  },
  {
    "id": "o8x",
    "name": "Commune de CHARRE"
  },
  {
    "id": "x2e",
    "name": "Commune de CHARRITTE-DE-BAS"
  },
  {
    "id": "v2u",
    "name": "Commune de CHERAUTE"
  },
  {
    "id": "i1p",
    "name": "Commune de Ciboure"
  },
  {
    "id": "i0q",
    "name": "Commune de CLARACQ"
  },
  {
    "id": "f2s",
    "name": "commune de Coarraze"
  },
  {
    "id": "w5s",
    "name": "Commune de CONCHEZ-DE-BEARN"
  },
  {
    "id": "q8z",
    "name": "Commune de CORBERE-ABERES"
  },
  {
    "id": "g4o",
    "name": "Commune de Cosledaa-Lube-Boast"
  },
  {
    "id": "e4i",
    "name": "Commune de COUBLUCQ"
  },
  {
    "id": "c9e",
    "name": "Commune de CROUSEILLES"
  },
  {
    "id": "a0x",
    "name": "Commune de CUQUERON"
  },
  {
    "id": "s5t",
    "name": "Commune de DENGUIN"
  },
  {
    "id": "x0v",
    "name": "Commune de DIUSSE"
  },
  {
    "id": "z4g",
    "name": "Commune de DOAZON"
  },
  {
    "id": "c1f",
    "name": "Commune de DOGNEN"
  },
  {
    "id": "v9r",
    "name": "Commune de DOMEZAIN-BERRAUTE"
  },
  {
    "id": "a1y",
    "name": "Commune de Doumy"
  },
  {
    "id": "x0y",
    "name": "Commune de FEAS"
  },
  {
    "id": "i6s",
    "name": "COMMUNE DE FICHOUS-RIUMAYOU"
  },
  {
    "id": "d4g",
    "name": "Commune de GABASTON"
  },
  {
    "id": "r5x",
    "name": "Commune de GABAT"
  },
  {
    "id": "u8q",
    "name": "Commune de GAMARTHE"
  },
  {
    "id": "t7u",
    "name": "Commune de GAN"
  },
  {
    "id": "e3p",
    "name": "Commune de GARINDEIN"
  },
  {
    "id": "o4e",
    "name": "Commune de GARLEDE-MONDEBAT"
  },
  {
    "id": "n8e",
    "name": "Commune de GARLIN"
  },
  {
    "id": "y6v",
    "name": "Commune de GAROS"
  },
  {
    "id": "m4j",
    "name": "Commune de GARRIS"
  },
  {
    "id": "l9d",
    "name": "Commune de GAYON"
  },
  {
    "id": "h1t",
    "name": "Commune de GELOS"
  },
  {
    "id": "e2j",
    "name": "Commune de GER"
  },
  {
    "id": "p8k",
    "name": "Commune de GERDEREST"
  },
  {
    "id": "t8r",
    "name": "Commune de GERE BELESTEN"
  },
  {
    "id": "o5s",
    "name": "commune de Géronce"
  },
  {
    "id": "m3u",
    "name": "Commune de GESTAS"
  },
  {
    "id": "g6a",
    "name": "Commune de GEUS-D'ARZACQ"
  },
  {
    "id": "y2d",
    "name": "Commune de GEÜS D'OLORON"
  },
  {
    "id": "i3m",
    "name": "Commune de GOES"
  },
  {
    "id": "c0l",
    "name": "Commune de GOMER"
  },
  {
    "id": "k0s",
    "name": "Commune de GOTEIN-LIBARRENX"
  },
  {
    "id": "a4e",
    "name": "Commune de GUETHARY"
  },
  {
    "id": "i9o",
    "name": "Commune de GUICHE"
  },
  {
    "id": "a2y",
    "name": "Commune de GUINARTHE-PARENTIES"
  },
  {
    "id": "z0e",
    "name": "Commune de GURMENÇON"
  },
  {
    "id": "y0w",
    "name": "Commune de GURS"
  },
  {
    "id": "e5v",
    "name": "Commune de HALSOU"
  },
  {
    "id": "v5b",
    "name": "Commune de HASPARREN"
  },
  {
    "id": "e5a",
    "name": "Commune de HAUT-de-BOSDARROS"
  },
  {
    "id": "u9c",
    "name": "Commune de HOURS"
  },
  {
    "id": "l4y",
    "name": "Commune de JASSES"
  },
  {
    "id": "e1o",
    "name": "Commune de JATXOU"
  },
  {
    "id": "e7q",
    "name": "Commune de JAXU"
  },
  {
    "id": "a3d",
    "name": "Commune de JURANÇON"
  },
  {
    "id": "k5t",
    "name": "Commune de JUXUE"
  },
  {
    "id": "a5v",
    "name": "Commune de L'HÔPITAL D'ORION"
  },
  {
    "id": "m4p",
    "name": "Commune de l'Hôpital-Saint-Blaise"
  },
  {
    "id": "d2i",
    "name": "Commune de LA BASTIDE-CLAIRENCE"
  },
  {
    "id": "f9r",
    "name": "Commune de LAA-MONDRANS"
  },
  {
    "id": "q8k",
    "name": "commune de Laas"
  },
  {
    "id": "m8e",
    "name": "Commune de LABASTIDE-CEZERACQ"
  },
  {
    "id": "o9x",
    "name": "Commune de LABASTIDE-MONREJEAU"
  },
  {
    "id": "n2n",
    "name": "Commune de LABASTIDE-VILLEFRANCHE"
  },
  {
    "id": "t6y",
    "name": "Commune de LABATMALE"
  },
  {
    "id": "g3i",
    "name": "Commune de LABATUT"
  },
  {
    "id": "n8z",
    "name": "Commune de LABEYRIE"
  },
  {
    "id": "n7v",
    "name": "Commune de LACADEE"
  },
  {
    "id": "o3i",
    "name": "Commune de LACARRE"
  },
  {
    "id": "a7x",
    "name": "Commune de LACARRY"
  },
  {
    "id": "n9m",
    "name": "Commune de LACOMMANDE"
  },
  {
    "id": "q4v",
    "name": "Commune de LACQ"
  },
  {
    "id": "n3x",
    "name": "Commune de LAGOR"
  },
  {
    "id": "x9c",
    "name": "Commune de LAGOS"
  },
  {
    "id": "h9s",
    "name": "Commune de LAHONCE"
  },
  {
    "id": "c3a",
    "name": "Commune de LAHONTAN"
  },
  {
    "id": "m1k",
    "name": "Commune de LAHOURCADE"
  },
  {
    "id": "s0f",
    "name": "Commune de LALONGUE"
  },
  {
    "id": "y9i",
    "name": "Commune de LALONQUETTE"
  },
  {
    "id": "c8u",
    "name": "Commune de LAMAYOU"
  },
  {
    "id": "t9z",
    "name": "Commune de LANNE-EN-BARETOUS"
  },
  {
    "id": "i4s",
    "name": "Commune de LANNECAUBE"
  },
  {
    "id": "i6o",
    "name": "Commune de LANNEPLAA"
  },
  {
    "id": "r0f",
    "name": "Commune de LANTABAT"
  },
  {
    "id": "o6n",
    "name": "Commune de LARCEVEAU"
  },
  {
    "id": "v5l",
    "name": "Commune de LAROIN"
  },
  {
    "id": "y7w",
    "name": "Commune de LARRAU"
  },
  {
    "id": "j6m",
    "name": "Commune de LARRESSORE"
  },
  {
    "id": "o3o",
    "name": "Commune de LARREULE"
  },
  {
    "id": "t9k",
    "name": "Commune de LARRIBAR-SORHAPURU"
  },
  {
    "id": "c4z",
    "name": "Commune de LARUNS"
  },
  {
    "id": "l4g",
    "name": "Commune de LASCLAVERIES"
  },
  {
    "id": "d6y",
    "name": "commune de Lasse"
  },
  {
    "id": "b6y",
    "name": "Commune de LASSERRE"
  },
  {
    "id": "c5p",
    "name": "Commune de LASSEUBE"
  },
  {
    "id": "f3x",
    "name": "COMMUNE DE LASSEUBETAT"
  },
  {
    "id": "k9l",
    "name": "Commune de LAY-LAMIDOU"
  },
  {
    "id": "a4s",
    "name": "Commune de Lecumberry"
  },
  {
    "id": "u3d",
    "name": "COMMUNE DE LEDEUIX"
  },
  {
    "id": "b3w",
    "name": "Commune de LEE"
  },
  {
    "id": "b5g",
    "name": "Commune de LEES-ATHAS"
  },
  {
    "id": "u2e",
    "name": "Commune de LEMBEYE"
  },
  {
    "id": "d1y",
    "name": "Commune de LEME"
  },
  {
    "id": "d4q",
    "name": "Commune de LEREN"
  },
  {
    "id": "i2w",
    "name": "Commune de LESCAR"
  },
  {
    "id": "a6m",
    "name": "Commune de LESCUN"
  },
  {
    "id": "k6x",
    "name": "Commune de Lespielle"
  },
  {
    "id": "s1l",
    "name": "Commune de LESPOURCY"
  },
  {
    "id": "s6b",
    "name": "Commune de LESTELLE-BETHARRAM"
  },
  {
    "id": "q4x",
    "name": "Commune de LICHANS-SUNHAR"
  },
  {
    "id": "j1p",
    "name": "Commune de LICHOS"
  },
  {
    "id": "c4q",
    "name": "Commune de LICQ-ATHEREY"
  },
  {
    "id": "u4m",
    "name": "Commune de LIMENDOUS"
  },
  {
    "id": "f1f",
    "name": "Commune de LIVRON"
  },
  {
    "id": "m4i",
    "name": "Commune de LOHITZUN-OYHERCQ"
  },
  {
    "id": "i4h",
    "name": "Commune de Lombia"
  },
  {
    "id": "w0x",
    "name": "Commune de LONCON"
  },
  {
    "id": "a3n",
    "name": "Commune de LONS"
  },
  {
    "id": "h7c",
    "name": "Commune de LOUBIENG"
  },
  {
    "id": "o8y",
    "name": "Commune de LOUHOSSOA"
  },
  {
    "id": "t7n",
    "name": "Commune de LOURDIOS-ICHERE"
  },
  {
    "id": "f8w",
    "name": "Commune de LOURENTIES"
  },
  {
    "id": "m3f",
    "name": "Commune de LOUVIE-JUZON"
  },
  {
    "id": "q2c",
    "name": "Commune de LOUVIE-SOUBIRON"
  },
  {
    "id": "t7p",
    "name": "Commune de LOUVIGNY"
  },
  {
    "id": "f3d",
    "name": "Commune de LUC-ARMAU"
  },
  {
    "id": "a2b",
    "name": "Commune de Lucarré"
  },
  {
    "id": "d1x",
    "name": "Commune de LUCGARIER"
  },
  {
    "id": "h3l",
    "name": "Commune de LUCQ-DE-BEARN"
  },
  {
    "id": "z8b",
    "name": "Commune de LURBE SAINT-CHRISTAU"
  },
  {
    "id": "a7v",
    "name": "Commune de LUSSAGNET-LUSSON"
  },
  {
    "id": "t3n",
    "name": "Commune de LUXE-SUMBERRAUTE"
  },
  {
    "id": "c5v",
    "name": "Commune de LYS"
  },
  {
    "id": "d6h",
    "name": "Commune de MACAYE"
  },
  {
    "id": "t8w",
    "name": "Commune de MALAUSSANNE"
  },
  {
    "id": "c2s",
    "name": "Commune de MASCARAAS-HARON"
  },
  {
    "id": "l0c",
    "name": "Commune de MASLACQ"
  },
  {
    "id": "b8p",
    "name": "Commune de MASPARRAUTE"
  },
  {
    "id": "v7v",
    "name": "Commune de MASPIE-LALONQUERE-JUILLACQ"
  },
  {
    "id": "u4a",
    "name": "Commune de MAUCOR"
  },
  {
    "id": "t9j",
    "name": "Commune de MAULEON-LICHARRE"
  },
  {
    "id": "z0h",
    "name": "Commune de MAURE"
  },
  {
    "id": "r5b",
    "name": "Commune de MAZERES-LEZONS"
  },
  {
    "id": "m1d",
    "name": "Commune de MAZEROLLES"
  },
  {
    "id": "h6b",
    "name": "Commune de MEHARIN"
  },
  {
    "id": "p5s",
    "name": "Commune de MEILLON"
  },
  {
    "id": "r5n",
    "name": "Commune de MENDIONDE"
  },
  {
    "id": "w9j",
    "name": "Commune de MENDITTE"
  },
  {
    "id": "a2v",
    "name": "COMMUNE DE MENDIVE"
  },
  {
    "id": "j1g",
    "name": "Commune de MERACQ"
  },
  {
    "id": "u2f",
    "name": "Commune de MERITEIN"
  },
  {
    "id": "d5t",
    "name": "Commune de MESPLEDE"
  },
  {
    "id": "d6m",
    "name": "Commune de MIALOS"
  },
  {
    "id": "a3t",
    "name": "commune de Miossens-Lanusse"
  },
  {
    "id": "d5r",
    "name": "Commune de MIREPEIX"
  },
  {
    "id": "j9g",
    "name": "Commune de MOMAS"
  },
  {
    "id": "x8k",
    "name": "Commune de Monassut-Audiracq"
  },
  {
    "id": "a6i",
    "name": "Commune de MONCAUP"
  },
  {
    "id": "k6b",
    "name": "Commune de MONCAYOLLE"
  },
  {
    "id": "f2o",
    "name": "Commune de MONCLA"
  },
  {
    "id": "p6l",
    "name": "Commune de MONEIN"
  },
  {
    "id": "v1a",
    "name": "Commune de MONPEZAT"
  },
  {
    "id": "a1g",
    "name": "COMMUNE DE MONSEGUR"
  },
  {
    "id": "u2x",
    "name": "Commune de MONT"
  },
  {
    "id": "f0g",
    "name": "Commune de MONT-DISSE"
  },
  {
    "id": "j0w",
    "name": "Commune de MONTAGUT"
  },
  {
    "id": "s3q",
    "name": "Commune de MONTANER"
  },
  {
    "id": "s3z",
    "name": "Commune de MONTARDON"
  },
  {
    "id": "w7p",
    "name": "Commune de MONTAUT"
  },
  {
    "id": "g6l",
    "name": "Commune de MONTFORT"
  },
  {
    "id": "d5g",
    "name": "Commune de MONTORY"
  },
  {
    "id": "f9f",
    "name": "Commune de MORLAAS"
  },
  {
    "id": "q0x",
    "name": "Commune de MORLANNE"
  },
  {
    "id": "q5m",
    "name": "Commune de MOUGUERRE"
  },
  {
    "id": "j7k",
    "name": "Commune de MOUHOUS"
  },
  {
    "id": "c7b",
    "name": "Commune de MOUMOUR"
  },
  {
    "id": "o5g",
    "name": "Commune de MOURENX"
  },
  {
    "id": "d6a",
    "name": "Commune de MUSCULDY"
  },
  {
    "id": "l5y",
    "name": "Commune de NABAS"
  },
  {
    "id": "b1o",
    "name": "Commune de NARCASTET"
  },
  {
    "id": "f4k",
    "name": "Commune de NARP"
  },
  {
    "id": "l8t",
    "name": "Commune de NAVAILLES-ANGOS"
  },
  {
    "id": "d0d",
    "name": "Commune de NAVARRENX"
  },
  {
    "id": "m3n",
    "name": "Commune de NAY"
  },
  {
    "id": "j2i",
    "name": "Commune de NOGUERES"
  },
  {
    "id": "b3z",
    "name": "Commune de NOUSTY"
  },
  {
    "id": "p9j",
    "name": "Commune de PAGOLLE"
  },
  {
    "id": "s6v",
    "name": "Commune de PARBAYSE"
  },
  {
    "id": "g1l",
    "name": "Commune de PARDIES"
  },
  {
    "id": "i5j",
    "name": "Commune de PARDIES-PIETAT"
  },
  {
    "id": "p4j",
    "name": "Commune de PAU"
  },
  {
    "id": "b4z",
    "name": "Commune de PEYRELONGUES-ABOS"
  },
  {
    "id": "l6f",
    "name": "Commune de PIETS-PLASENCE-MOUSTROU"
  },
  {
    "id": "m7x",
    "name": "Commune de Poey d'Oloron"
  },
  {
    "id": "x6d",
    "name": "Commune de POEY-DE-LESCAR"
  },
  {
    "id": "q3m",
    "name": "Commune de POMPS"
  },
  {
    "id": "t0r",
    "name": "Commune de PONSON-DEBAT-POUTS"
  },
  {
    "id": "h3q",
    "name": "COMMUNE DE PONSON-DESSUS"
  },
  {
    "id": "z9k",
    "name": "Commune de PONTACQ"
  },
  {
    "id": "d1n",
    "name": "Commune de PONTIACQ-VIELLEPINTE"
  },
  {
    "id": "z8i",
    "name": "COMMUNE DE PORTET"
  },
  {
    "id": "r1d",
    "name": "Commune de POULIACQ"
  },
  {
    "id": "g9k",
    "name": "Commune de POURSIUGUES-BOUCOUE"
  },
  {
    "id": "r6o",
    "name": "Commune de PRECHACQ-JOSBAIG"
  },
  {
    "id": "h2f",
    "name": "Commune de PRECHACQ-NAVARRENX"
  },
  {
    "id": "u8e",
    "name": "Commune de PRECILHON"
  },
  {
    "id": "a4k",
    "name": "Commune de PUYOO"
  },
  {
    "id": "o0z",
    "name": "Commune de REBENACQ"
  },
  {
    "id": "a4b",
    "name": "Commune de RIUPEYROUS"
  },
  {
    "id": "a5y",
    "name": "Commune de RIVEHAUTE"
  },
  {
    "id": "u3z",
    "name": "Commune de Rontignon"
  },
  {
    "id": "b0t",
    "name": "Commune de ROQUIAGUE"
  },
  {
    "id": "e6w",
    "name": "Commune de SAINT-ABIT"
  },
  {
    "id": "o8a",
    "name": "Commune de SAINT-ARMOU"
  },
  {
    "id": "k6p",
    "name": "Commune de SAINT-BOES"
  },
  {
    "id": "q6o",
    "name": "Commune de SAINT-CASTIN"
  },
  {
    "id": "w7k",
    "name": "Commune de SAINT-DOS"
  },
  {
    "id": "b6u",
    "name": "Commune de SAINT-ESTEBEN"
  },
  {
    "id": "f4r",
    "name": "Commune de SAINT-ETIENNE-DE-BAIGORRY"
  },
  {
    "id": "g2g",
    "name": "Commune de SAINT-FAUST"
  },
  {
    "id": "i4w",
    "name": "Commune de SAINT-GIRONS-EN-BEARN"
  },
  {
    "id": "h5x",
    "name": "Commune de SAINT-GLADIE-ARRIVE-MUNEIN"
  },
  {
    "id": "x0m",
    "name": "Commune de SAINT-GOIN"
  },
  {
    "id": "a5u",
    "name": "Commune de SAINT-JAMMES"
  },
  {
    "id": "l3q",
    "name": "commune de Saint-Jean-de-Luz"
  },
  {
    "id": "u9p",
    "name": "Commune de SAINT-JEAN-LE-VIEUX"
  },
  {
    "id": "g9z",
    "name": "Commune de SAINT-JEAN-PIED-DE-PORT"
  },
  {
    "id": "i7l",
    "name": "Commune de SAINT-JEAN-POUDGE"
  },
  {
    "id": "p3h",
    "name": "Commune de SAINT-JUST-IBARRE"
  },
  {
    "id": "f7o",
    "name": "Commune de SAINT-LAURENT-BRETAGNE"
  },
  {
    "id": "j5e",
    "name": "Commune de SAINT-MARTIN-D'ARROSSA"
  },
  {
    "id": "h4j",
    "name": "Commune de SAINT-MARTIN-D'ARBEROUE"
  },
  {
    "id": "y2p",
    "name": "Commune de SAINT-MEDARD"
  },
  {
    "id": "h6k",
    "name": "Commune de Saint-Michel"
  },
  {
    "id": "w7g",
    "name": "Commune de SAINT-PALAIS"
  },
  {
    "id": "d1i",
    "name": "Commune de SAINT-PE-DE-LEREN"
  },
  {
    "id": "w5c",
    "name": "Commune de SAINT-PEE-SUR-NIVELLE"
  },
  {
    "id": "a7w",
    "name": "Commune de SAINT-PIERRE-D'IRUBE"
  },
  {
    "id": "l1f",
    "name": "Commune de SAINT-VINCENT"
  },
  {
    "id": "n4n",
    "name": "Commune de SAINTE-ENGRACE"
  },
  {
    "id": "n3g",
    "name": "Commune de SALIES-DE-BEARN"
  },
  {
    "id": "i5u",
    "name": "Commune de SALLES-MONGISCARD"
  },
  {
    "id": "n1k",
    "name": "Commune de SALLESPISSE"
  },
  {
    "id": "p2q",
    "name": "Commune de SAMES"
  },
  {
    "id": "s7j",
    "name": "Commune de SAMSONS-LION"
  },
  {
    "id": "e4f",
    "name": "Commune de SARE"
  },
  {
    "id": "r8j",
    "name": "Commune de SARPOURENX"
  },
  {
    "id": "r0v",
    "name": "Commune de SARRANCE"
  },
  {
    "id": "b1f",
    "name": "Commune de SAUBOLE"
  },
  {
    "id": "e3c",
    "name": "Commune de SAUCEDE"
  },
  {
    "id": "s9f",
    "name": "COMMUNE DE SAUGUIS SAINT ETIENNE"
  },
  {
    "id": "f4q",
    "name": "Commune de Sault-de-Navailles"
  },
  {
    "id": "z8s",
    "name": "Commune de SAUVAGNON"
  },
  {
    "id": "v9f",
    "name": "Commune de SAUVELADE"
  },
  {
    "id": "h4v",
    "name": "Commune de SAUVETERRE-DE-BEARN"
  },
  {
    "id": "h4y",
    "name": "Commune de SEBY"
  },
  {
    "id": "y8m",
    "name": "Commune de SEDZE-MAUBECQ"
  },
  {
    "id": "w1z",
    "name": "Commune de SEDZERE"
  },
  {
    "id": "p0t",
    "name": "Commune de SEMEACQ-BLACHON"
  },
  {
    "id": "s0g",
    "name": "Commune de SENDETS"
  },
  {
    "id": "b1d",
    "name": "Commune de SERRES-CASTET"
  },
  {
    "id": "b8c",
    "name": "Commune de SERRES-MORLAAS"
  },
  {
    "id": "e3l",
    "name": "Commune de SERRES-SAINTE-MARIE"
  },
  {
    "id": "k6s",
    "name": "Commune de SEVIGNACQ"
  },
  {
    "id": "e5t",
    "name": "Commune de Sévignacq-Meyracq"
  },
  {
    "id": "i3q",
    "name": "Commune de SIMACOURBE"
  },
  {
    "id": "v8x",
    "name": "Commune de SIROS"
  },
  {
    "id": "b6v",
    "name": "Commune de SOUMOULOU"
  },
  {
    "id": "t3k",
    "name": "Commune de SOURAIDE"
  },
  {
    "id": "s4y",
    "name": "Commune de SUHESCUN"
  },
  {
    "id": "k0m",
    "name": "Commune de SUS"
  },
  {
    "id": "x9o",
    "name": "Commune de SUSMIOU"
  },
  {
    "id": "a3e",
    "name": "Commune de TABAILLE-USQUAIN"
  },
  {
    "id": "t9x",
    "name": "Commune de TADOUSSE-USSAU"
  },
  {
    "id": "c9w",
    "name": "Commune de Tardets-Sorholus"
  },
  {
    "id": "d4n",
    "name": "Commune de TARON-SADIRAC-VIELLENAVE"
  },
  {
    "id": "m0m",
    "name": "Commune de TARSACQ"
  },
  {
    "id": "p6p",
    "name": "Commune de URT"
  },
  {
    "id": "o7e",
    "name": "Commune de VERDETS"
  },
  {
    "id": "a2n",
    "name": "Commune de VIALER"
  },
  {
    "id": "v8c",
    "name": "Commune de Viellenave d'Arthez"
  },
  {
    "id": "a5a",
    "name": "Commune de VIELLENAVE DE NAVARRENX"
  },
  {
    "id": "c3e",
    "name": "Commune de VIELLESEGURE"
  },
  {
    "id": "a0l",
    "name": "Commune de Vignes"
  },
  {
    "id": "z6e",
    "name": "Commune de VILLEFRANQUE"
  },
  {
    "id": "i9v",
    "name": "Commune de VIODOS-ABENSE-DE-BAS"
  },
  {
    "id": "l7t",
    "name": "Commune de VIVEN"
  },
  {
    "id": "d3w",
    "name": "Commune des Aldudes"
  },
  {
    "id": "f3j",
    "name": "Commune des EAUX-BONNES"
  },
  {
    "id": "a2s",
    "name": "CONSEIL DES ELUS DU PAYS BASQUE"
  },
  {
    "id": "a2e",
    "name": "Conservatoire de musique de Bayonne"
  },
  {
    "id": "t5y",
    "name": "Département des Pyrénées-Atlantiques"
  },
  {
    "id": "r0n",
    "name": "E.P.I.C. BIARRITZ TOURISME"
  },
  {
    "id": "f0w",
    "name": "ECOLE SUPERIEURE D'ART DES PYRENEES - PAU TARBES"
  },
  {
    "id": "b7e",
    "name": "EHPAD MAISON DE RETRAITE DU LUY DE BEARN"
  },
  {
    "id": "j6n",
    "name": "EPIC ATABAL"
  },
  {
    "id": "n1t",
    "name": "Etablissement Public Foncier Local Béarn Pyrénées"
  },
  {
    "id": "d2h",
    "name": "Etablissement public foncier local Pays Basque"
  },
  {
    "id": "b7u",
    "name": "EXTERRA"
  },
  {
    "id": "d7e",
    "name": "Fédération des Associations Foncières Pastorales et des Groupements Pastoraux des Pyrénées-Atlantiques"
  },
  {
    "id": "a5o",
    "name": "G.E.C.T Eurorégion Aquitaine-Euskadi-Navarre"
  },
  {
    "id": "a6l",
    "name": "GIP CHEMPARC"
  },
  {
    "id": "s5p",
    "name": "HABITAT SUD ATLANTIC"
  },
  {
    "id": "a2r",
    "name": "HABITELEM"
  },
  {
    "id": "r6d",
    "name": "L'Eau d'ici - Etablissement public local de production d'eau potable du Pays Basque et Sud Landes"
  },
  {
    "id": "a1k",
    "name": "LABORATOIRE DES PYRENEES ET DES LANDES"
  },
  {
    "id": "b0k",
    "name": "Lotissement communal d'ASAP-ARROS"
  },
  {
    "id": "a4f",
    "name": "Office 64 de l'habitat"
  },
  {
    "id": "a3h",
    "name": "Office de tourisme Coeur de Béarn"
  },
  {
    "id": "a5g",
    "name": "OFFICE DE TOURISME COMMUNAUTAIRE PAU PYRENEES"
  },
  {
    "id": "d1e",
    "name": "Office de tourisme de la Soule"
  },
  {
    "id": "a5d",
    "name": "Office de tourisme du Béarn et des Gaves"
  },
  {
    "id": "d4v",
    "name": "Office Palois de l'Habitat"
  },
  {
    "id": "e7v",
    "name": "Office Public de l'Habitat de Bayonne"
  },
  {
    "id": "u5g",
    "name": "Office Public de la Langue Basque"
  },
  {
    "id": "r1i",
    "name": "Office Public de la Langue Basque"
  },
  {
    "id": "a7g",
    "name": "Pôle métropolitain Pays de Béarn"
  },
  {
    "id": "i4z",
    "name": "R.P.I. en pays d'ARTHEZ"
  },
  {
    "id": "a2k",
    "name": "Régie de production de chaleur du SDEPA"
  },
  {
    "id": "a1p",
    "name": "Régie du conservatoire à rayonnement régional Maurice Ravel de la CAPB"
  },
  {
    "id": "a5w",
    "name": "Régie photovoltaïque du SDEPA"
  },
  {
    "id": "x6g",
    "name": "RESEAU SPORT 64 - CENTRE NELSON PAILLOU"
  },
  {
    "id": "e4y",
    "name": "RPI GOES ESTIALESCQ"
  },
  {
    "id": "g7q",
    "name": "S.A.E.P. d'ARZACQ"
  },
  {
    "id": "i2j",
    "name": "S.A.E.P. de Crouseilles"
  },
  {
    "id": "r7z",
    "name": "S.A.E.P. de la région de GARLIN"
  },
  {
    "id": "l7g",
    "name": "S.A.E.P. de la région de LESCAR"
  },
  {
    "id": "s0j",
    "name": "S.A.E.P. de LEMBEYE"
  },
  {
    "id": "e7d",
    "name": "S.A.E.P. du pays de Mixe"
  },
  {
    "id": "o2z",
    "name": "S.A.E.P. du pays de SOULE"
  },
  {
    "id": "w4k",
    "name": "S.I. assainissement plaine de l'Ousse"
  },
  {
    "id": "w4c",
    "name": "S.I. d'assainissement de Bescat/Sévignacq-Meyracq/Ste Colome"
  },
  {
    "id": "t9o",
    "name": "S.I. d'aide matérielle à la scolarisation de la vallée d'Aspe"
  },
  {
    "id": "q1p",
    "name": "S.I. de défense C/ les inondations du gave de PAU"
  },
  {
    "id": "z7g",
    "name": "S.I. de la baie de SAINT-JEAN-DE-LUZ et CIBOURE"
  },
  {
    "id": "f4g",
    "name": "S.I. de protection des berges de l'Adour Maritime et affluents "
  },
  {
    "id": "a9h",
    "name": "S.I. DEFENSE C/INONDATIONS BASSIN DU LAGOIN"
  },
  {
    "id": "q8n",
    "name": "S.I. des cinq rivières"
  },
  {
    "id": "s5m",
    "name": "S.I. Transport scolaire RIUPEYROUS - ST LAURENT BRETAGNE"
  },
  {
    "id": "o6d",
    "name": "S.I.A.E.P de Mendionde et de Bonloc"
  },
  {
    "id": "q8w",
    "name": "S.I.A.E.P.  AREN PRECHACQ-JOSBAIG"
  },
  {
    "id": "k9p",
    "name": "S.I.A.E.P. d'OGEU-LES-BAINS"
  },
  {
    "id": "w4o",
    "name": "S.I.A.E.P. de l'ARBEROUE"
  },
  {
    "id": "a1b",
    "name": "S.I.A.E.P. de l'Oztabarret"
  },
  {
    "id": "u0p",
    "name": "S.I.A.E.P. de la Plaine de Nay"
  },
  {
    "id": "b5m",
    "name": "S.I.A.E.P. de la région d'Ainhice"
  },
  {
    "id": "j0x",
    "name": "S.I.A.E.P. de la région de MONTANER"
  },
  {
    "id": "p9u",
    "name": "S.I.A.E.P. de la région de SAUVETERRE-DE-BEARN"
  },
  {
    "id": "j6k",
    "name": "S.I.A.E.P. de la région du Saleys"
  },
  {
    "id": "v9c",
    "name": "S.I.A.E.P. de la Vallée de l'Ousse"
  },
  {
    "id": "a4z",
    "name": "S.I.A.E.P. de NAY-OUEST"
  },
  {
    "id": "y3n",
    "name": "S.I.A.E.P. du Saleys et des Gaves"
  },
  {
    "id": "r5o",
    "name": "S.I.A.E.P. DU VIC BILH MONTANERES"
  },
  {
    "id": "p2z",
    "name": "S.I.A.E.P. Luy et Gabas"
  },
  {
    "id": "k9y",
    "name": "S.I.A.E.P. LUY GABAS LEES"
  },
  {
    "id": "n2v",
    "name": "S.I.A.E.P. MACAYE-LOUHOSSOA"
  },
  {
    "id": "g4p",
    "name": "S.I.R.P.  GEUS D'ARZACQ / LUY DE BEARN"
  },
  {
    "id": "e0v",
    "name": "S.I.R.P. ARBERATS-ARBOUET-AROUE-ETCHARRY"
  },
  {
    "id": "t0f",
    "name": "S.I.R.P. Auterrive / Léren / Saint-Pé-de-Léren / Saint-Dos"
  },
  {
    "id": "y4i",
    "name": "S.I.R.P. LABASTIDE-CEZERACQ LABASTIDE-MONREJEAU"
  },
  {
    "id": "a9s",
    "name": "S.I.R.P. OS-MARSILLON/ABIDOS"
  },
  {
    "id": "f8b",
    "name": "S.I.R.P. SAINT-MICHEL / ESTERENCUBY"
  },
  {
    "id": "n1z",
    "name": "S.I.V.O.S. de la vallée du LYS"
  },
  {
    "id": "c2y",
    "name": "S.I.V.U.R.P. Osserain Guinarthe"
  },
  {
    "id": "x2o",
    "name": "S.P.I.D.E.P. du CASTETS"
  },
  {
    "id": "t9w",
    "name": "S.R.P.I ARBAILLA"
  },
  {
    "id": "e7p",
    "name": "S.R.P.I. ISPACHOURY"
  },
  {
    "id": "a1i",
    "name": "Saint-Jean-de-Luz Animations et Commerces"
  },
  {
    "id": "m8s",
    "name": "SDIS DE PAU"
  },
  {
    "id": "y4j",
    "name": "SEM BEARNAISE D'HABITAT"
  },
  {
    "id": "a6h",
    "name": "SEM de Gelos"
  },
  {
    "id": "f6i",
    "name": "SEML Créaticité"
  },
  {
    "id": "u1i",
    "name": "SEPA"
  },
  {
    "id": "r2f",
    "name": "Service d'Assainissement de Vielleségure"
  },
  {
    "id": "y7v",
    "name": "SIAEP NAVARRENX"
  },
  {
    "id": "k6k",
    "name": "SIAEP Saint-Jean-Le-Vieux Bussunarits"
  },
  {
    "id": "b7i",
    "name": "SICTOM HAUT BEARN"
  },
  {
    "id": "h5t",
    "name": "SIECTOM des COTEAUX BEARN ADOUR"
  },
  {
    "id": "c8h",
    "name": "SIRP ASASP LURBE ESCOT"
  },
  {
    "id": "a2c",
    "name": "SIRP Bielle Bilhères-en-Ossau"
  },
  {
    "id": "r2g",
    "name": "SIVOM d'Arbonne Arcangues Bassussarry"
  },
  {
    "id": "h3s",
    "name": "SIVOM DU CANTON DE LASSEUBE"
  },
  {
    "id": "u9t",
    "name": "Sivom du canton de MONTANER"
  },
  {
    "id": "n4r",
    "name": "SIVOM du canton de TARDETS"
  },
  {
    "id": "o2f",
    "name": "SIVOS DU PALAY"
  },
  {
    "id": "n9q",
    "name": "SIVOS ESCOUBES SEVIGNACQ"
  },
  {
    "id": "b3p",
    "name": "SIVOS GAZTELAIA"
  },
  {
    "id": "w7n",
    "name": "SIVOS RECRE A 5"
  },
  {
    "id": "a3a",
    "name": "SIVOS SAINT-VINCENT ET LABATMALE"
  },
  {
    "id": "o2i",
    "name": "SIVOS SIMACOURBE LALONGUE LESPIELLE"
  },
  {
    "id": "a8h",
    "name": "SIVU ACAMT"
  },
  {
    "id": "i8s",
    "name": "Sivu BAI GUREA"
  },
  {
    "id": "c1a",
    "name": "SIVU BALANSUN CASTETIS"
  },
  {
    "id": "f4u",
    "name": "SIVU Barétous et Haute Soule"
  },
  {
    "id": "d3q",
    "name": "SIVU BORDES ASSAT"
  },
  {
    "id": "y5c",
    "name": "SIVU Centre équestre de NARCASTET"
  },
  {
    "id": "b9r",
    "name": "SIVU d'aide à domicile de la Plaine de NAY"
  },
  {
    "id": "d1w",
    "name": "SIVU d'assainissement de la vallée d'OSSAU"
  },
  {
    "id": "x7o",
    "name": "SIVU d'assainissement Gave et Lagoin"
  },
  {
    "id": "k9m",
    "name": "SIVU de la voirie de la régon de GARLIN"
  },
  {
    "id": "l8y",
    "name": "SIVU de la voirie de LEMBEYE"
  },
  {
    "id": "h4b",
    "name": "SIVU de MONGISCARD"
  },
  {
    "id": "m5n",
    "name": "SIVU DES ECOLES D'OSTIBARET"
  },
  {
    "id": "g9d",
    "name": "SIVU des Ecoles du Luy"
  },
  {
    "id": "c0u",
    "name": "SIVU des GAVES et du SALEYS"
  },
  {
    "id": "l2s",
    "name": "SIVU des villages réunis LANNEPLAA SALLES-MONGISCARD"
  },
  {
    "id": "u8s",
    "name": "SIVU du LAYOU"
  },
  {
    "id": "y3j",
    "name": "SIVU du LEES et affluents"
  },
  {
    "id": "i9e",
    "name": "SIVU DU LOURDIOS"
  },
  {
    "id": "a5c",
    "name": "SIVU du RPI de Beuste-Lagos"
  },
  {
    "id": "a4p",
    "name": "SIVU ENTRE DEUX LEES"
  },
  {
    "id": "v4b",
    "name": "SIVU entretien voirie et espaces verts de Mazerolles"
  },
  {
    "id": "p8o",
    "name": "SIVU ERREBI"
  },
  {
    "id": "k4r",
    "name": "SIVU ERROBI"
  },
  {
    "id": "d9g",
    "name": "SIVU EVBEV de Barinque"
  },
  {
    "id": "w5w",
    "name": "Sivu Gure Eskola"
  },
  {
    "id": "a7h",
    "name": "SIVU Ikas Bide"
  },
  {
    "id": "x3t",
    "name": "SIVU La Verna"
  },
  {
    "id": "a3b",
    "name": "SIVU LATAILLADE"
  },
  {
    "id": "r4b",
    "name": "SIVU Natura 2000 Mondarrain Artzamendi"
  },
  {
    "id": "n5b",
    "name": "SIVU OZTIBARRE GARBI"
  },
  {
    "id": "a5f",
    "name": "SIVU PINOCCHIO"
  },
  {
    "id": "a1m",
    "name": "SIVU RP ELGARREKIN IKAS"
  },
  {
    "id": "a6d",
    "name": "SIVU RPI ASASP ARROS LURBE SAINT CHRISTAU ESCOT"
  },
  {
    "id": "a1v",
    "name": "SIVU RPI BUZY BUZIET"
  },
  {
    "id": "m9x",
    "name": "SIVU RPI d'Issor et de Lourdios-Ichere"
  },
  {
    "id": "t2l",
    "name": "SIVU scolaire de BIRON, CASTETNER et SARPOURENX"
  },
  {
    "id": "v0c",
    "name": "SIVU scolaire Eslourenties-Limendous-Lourenties"
  },
  {
    "id": "l7n",
    "name": "Sivu transport scolaire Méharin Armendarits"
  },
  {
    "id": "x8h",
    "name": "SIVU VAL DE L'OUSSE"
  },
  {
    "id": "l5b",
    "name": "SMEP de la région de JURANÇON"
  },
  {
    "id": "v5s",
    "name": "SMO LaFibre64"
  },
  {
    "id": "f8o",
    "name": "Société d'Economie Mixte du Luy de Béarn"
  },
  {
    "id": "m9w",
    "name": "Société d'Irrigation de la Plaine du Lagoin"
  },
  {
    "id": "j6b",
    "name": "Syndicat ADOUR-URSUIA"
  },
  {
    "id": "c5j",
    "name": "Syndicat d'énergie des Pyrénées-Atlantiques"
  },
  {
    "id": "q4g",
    "name": "Syndicat d'ISSAUX"
  },
  {
    "id": "o3m",
    "name": "Syndicat d'aménagement hydraulique du bassin de l'Ousse"
  },
  {
    "id": "q2m",
    "name": "Syndicat d'Assainissement Autonome de l'Adour"
  },
  {
    "id": "w6e",
    "name": "SYNDICAT D'ASSAINISSEMENT DE L'ESCOU"
  },
  {
    "id": "n8f",
    "name": "SYNDICAT D'ASSAINISSEMENT DE LA PORTE D'ASPE"
  },
  {
    "id": "q5s",
    "name": "Syndicat d'Assainissement de NAVARRENX"
  },
  {
    "id": "o4w",
    "name": "Syndicat d'assainissement de Nay à Baliros"
  },
  {
    "id": "b9h",
    "name": "Syndicat d'assainissement du Pays de Nay"
  },
  {
    "id": "t3h",
    "name": "Syndicat d'assainissement du pays de Soule"
  },
  {
    "id": "k3v",
    "name": "Syndicat d'Eau de la vallée d'Ossau"
  },
  {
    "id": "o3l",
    "name": "Syndicat d'eau et d'assainissement du Pays de Nay"
  },
  {
    "id": "e9v",
    "name": "Syndicat d'eau potable du Pays de Nay"
  },
  {
    "id": "a4o",
    "name": "Syndicat de Bugangue"
  },
  {
    "id": "t7h",
    "name": "Syndicat de Grechez"
  },
  {
    "id": "q7z",
    "name": "Syndicat de l'UHABIA"
  },
  {
    "id": "j4s",
    "name": "Syndicat de la zone artisanale d'AYHERRE"
  },
  {
    "id": "y7t",
    "name": "Syndicat de Production d'eau d'Auterrive"
  },
  {
    "id": "x1j",
    "name": "Syndicat de ramassage scolaire Gabat/Amendeuix-Oneix/Ilharre"
  },
  {
    "id": "a5j",
    "name": "Syndicat de Regroupement Pédagogique Castetnau-Camblong Sus"
  },
  {
    "id": "c7j",
    "name": "Syndicat de regroupement scolaire GLAM"
  },
  {
    "id": "a5m",
    "name": "Syndicat de TERMY"
  },
  {
    "id": "t0z",
    "name": "Syndicat des Eaux Luy Gabas Lées"
  },
  {
    "id": "a1r",
    "name": "Syndicat des écoles de la région de GARLIN"
  },
  {
    "id": "g4y",
    "name": "Syndicat des écoles Gaveausset"
  },
  {
    "id": "w6o",
    "name": "Syndicat des Mobilités Pays Basque Adour"
  },
  {
    "id": "x9v",
    "name": "Syndicat du LABAY"
  },
  {
    "id": "y9j",
    "name": "syndicat d’étude et aménagement du bassin versant du Vert"
  },
  {
    "id": "a5i",
    "name": "Syndicat Eau Assainissement Bearn Bigorre"
  },
  {
    "id": "a1x",
    "name": "Syndicat Électrification du Bas-Ossau"
  },
  {
    "id": "p1z",
    "name": "Syndicat Forestier des Chênaies des Vallées Basques et Béarnaises"
  },
  {
    "id": "a1e",
    "name": "Syndicat GAMARTHE LACARRE"
  },
  {
    "id": "r5g",
    "name": "Syndicat immeuble perception de Navarrenx"
  },
  {
    "id": "a2d",
    "name": "Syndicat Intercommunal à Vocation Unique Bigabat"
  },
  {
    "id": "a4h",
    "name": "Syndicat Intercommunal AUBIN AUGA BOURNOS DOUMY"
  },
  {
    "id": "a2a",
    "name": "Syndicat Intercommunal d'Adduction d'Eau Potable de la Vallée d'Ossau"
  },
  {
    "id": "l0p",
    "name": "Syndicat intercommunal d'aménagement de la zone ILBARRITZ-MOURISCOT"
  },
  {
    "id": "y4a",
    "name": "Syndicat intercommunal d'ARTHEZ-DE-BEARN"
  },
  {
    "id": "a2q",
    "name": "Syndicat intercommunal d'irrigation ANOS SAINT-ARMOU"
  },
  {
    "id": "u5r",
    "name": "Syndicat Intercommunal d'Assainissement de SAINT-PALAIS"
  },
  {
    "id": "f9m",
    "name": "Syndicat intercommunal d'assainissement du Luy de Béarn"
  },
  {
    "id": "j8o",
    "name": "Syndicat Intercommunal d'Assainissement UR GARBI"
  },
  {
    "id": "p9l",
    "name": "Syndicat intercommunal d'élimination des déchets de la côte basque sud"
  },
  {
    "id": "p2l",
    "name": "Syndicat Intercommunal de la Basse Vallée de l’Untxin et de Voirie de Ciboure et Urrugne"
  },
  {
    "id": "t7j",
    "name": "Syndicat intercommunal de LAGOR"
  },
  {
    "id": "a4r",
    "name": "Syndicat Intercommunal de Regroupement Pédagogique SAINTE COLOME-SEVIGNACQ MEYRACQ"
  },
  {
    "id": "b2t",
    "name": "Syndicat intercommunal des écoles de Joncaux et de Béhobie"
  },
  {
    "id": "w8u",
    "name": "Syndicat intercommunal du soutien à la culture basque"
  },
  {
    "id": "m8l",
    "name": "Syndicat Intercommunal PONTIACQ-VIELLEPINTE LAMAYOU"
  },
  {
    "id": "y1n",
    "name": "Syndicat intercommunal Saint-Armou Anos"
  },
  {
    "id": "i1d",
    "name": "Syndicat mixte bassin versant de la Nive"
  },
  {
    "id": "m1i",
    "name": "Syndicat mixte BIZI GARBIA"
  },
  {
    "id": "a5p",
    "name": "Syndicat Mixte d'Eau et d'Assainissement Gave et Baïse"
  },
  {
    "id": "j4b",
    "name": "Syndicat mixte d'A.E.P. du Nord-Est de PAU"
  },
  {
    "id": "j5v",
    "name": "Syndicat Mixte d'Alimentation en eau potable URA"
  },
  {
    "id": "o3f",
    "name": "Syndicat mixte d'aménagement de la zone d'Ametzondo"
  },
  {
    "id": "f5v",
    "name": "Syndicat Mixte d'Assainissement Collectif et non collectif URA"
  },
  {
    "id": "n7d",
    "name": "Syndicat mixte d'assainissement du Luy de Béarn"
  },
  {
    "id": "l3s",
    "name": "Syndicat mixte d'eau et d'assainissement de la vallée de l'Ousse "
  },
  {
    "id": "a2w",
    "name": "Syndicat mixte d'eau potable de la région d'Orthez"
  },
  {
    "id": "g2j",
    "name": "Syndicat mixte d'études de la liaison routière PAU-OLORON"
  },
  {
    "id": "b6n",
    "name": "Syndicat Mixte dAménagement du Centre Européen de Fret"
  },
  {
    "id": "m0p",
    "name": "Syndicat mixte de BIL TA GARBI"
  },
  {
    "id": "a6b",
    "name": "Syndicat Mixte de l'Adour Maritime et ses affluents"
  },
  {
    "id": "a9t",
    "name": "Syndicat mixte de l'aéroport de PAU-PYRENEES"
  },
  {
    "id": "r2b",
    "name": "Syndicat Mixte de l'Ouhabia"
  },
  {
    "id": "y8b",
    "name": "Syndicat mixte de la base de loisirs d’orthez Biron"
  },
  {
    "id": "n4e",
    "name": "Syndicat Mixte de la Gendarmerie de GARLIN"
  },
  {
    "id": "i8q",
    "name": "Syndicat mixte de la Nive maritime"
  },
  {
    "id": "z0y",
    "name": "Syndicat mixte de la Pierre Saint Martin"
  },
  {
    "id": "a1d",
    "name": "Syndicat Mixte de l’Adour Maritime et Affluents (S.M.A.MA.)"
  },
  {
    "id": "e9m",
    "name": "Syndicat mixte des écoles de MORLANNE et CASTEIDE-CANDAU"
  },
  {
    "id": "d8t",
    "name": "Syndicat Mixte DES GAVES D'OLORON et de MAULEON"
  },
  {
    "id": "n9b",
    "name": "Syndicat mixte des gaves d'Oloron, Aspe, Ossau et leurs affluents "
  },
  {
    "id": "j2o",
    "name": "Syndicat mixte du bassin du gave de PAU"
  },
  {
    "id": "a5q",
    "name": "Syndicat mixte du camp de Gurs"
  },
  {
    "id": "p2d",
    "name": "Syndicat mixte du Haut Béarn"
  },
  {
    "id": "d3i",
    "name": "Syndicat mixte du musée basque et de l'histoire de BAYONNE"
  },
  {
    "id": "h5m",
    "name": "SYNDICAT MIXTE DU NORD BEARN"
  },
  {
    "id": "d8m",
    "name": "Syndicat mixte du Pays Oloron Haut Béarn"
  },
  {
    "id": "m5w",
    "name": "Syndicat Mixte du Pôle Aéronautique de Bordes-Assat"
  },
  {
    "id": "t3u",
    "name": "Syndicat mixte du SCOT du Pays Basque et du Seignanx"
  },
  {
    "id": "z6n",
    "name": "Syndicat Mixte eau et assainissement des TROIS CANTONS"
  },
  {
    "id": "a4t",
    "name": "Syndicat Mixte Eau et Assainissement Gave et Baïse (ancien)"
  },
  {
    "id": "z9a",
    "name": "Syndicat mixte GARBIKI"
  },
  {
    "id": "a5e",
    "name": "SYNDICAT MIXTE GARLIN PYRENEES"
  },
  {
    "id": "h1n",
    "name": "Syndicat mixte Kosta Garbia"
  },
  {
    "id": "m7o",
    "name": "Syndicat mixte la crèche de l'Arche"
  },
  {
    "id": "c5o",
    "name": "Syndicat Mixte Pau Bearn Pyrénées Mobilité"
  },
  {
    "id": "f0x",
    "name": "Syndicat mixte pour le traitement des déchets du bassin est du Béarn"
  },
  {
    "id": "h8b",
    "name": "Syndicat Mixte Traitement des Boues"
  },
  {
    "id": "s6y",
    "name": "Syndicat pour la ZA ETXECOLU BARDOS"
  },
  {
    "id": "t6w",
    "name": "Syndicat RPI AMOBA"
  },
  {
    "id": "a6e",
    "name": "SYNDICAT RPI ERGARAY"
  },
  {
    "id": "z1j",
    "name": "Syndicat scolaire ARGELOS ASTIS"
  },
  {
    "id": "a4d",
    "name": "Syndicat TXAKURRAK"
  },
  {
    "id": "j0a",
    "name": "UD64"
  },
  {
    "id": "UD64",
    "name": "UD64"
  }
]
